cloudregion/__init__.py
cloudregion/integrations.py
cloudregion/region.py
cloudregion/region_data.py
cloudregion-0.0.3.dist-info/METADATA
cloudregion-0.0.3.dist-info/WHEEL
cloudregion-0.0.3.dist-info/licenses/LICENSE
cloudregion-0.0.3.dist-info/RECORD
