Metadata-Version: 2.4
Name: cloudregion
Version: 0.0.3
Summary: Simple Python library that converts between cloud region names across AWS/Azure/GCP.
Project-URL: Homepage, https://prassanna.io/cloudregion/
Project-URL: Repository, https://github.com/prassanna-ravishankar/cloudregion
Project-URL: Documentation, https://prassanna.io/cloudregion/
Author-email: "Prass, The Nomadic Coder" <me@prassanna.io>
License-File: LICENSE
Keywords: python
Classifier: Intended Audience :: Developers
Classifier: Programming Language :: Python
Classifier: Programming Language :: Python :: 3
Classifier: Programming Language :: Python :: 3.9
Classifier: Programming Language :: Python :: 3.10
Classifier: Programming Language :: Python :: 3.11
Classifier: Programming Language :: Python :: 3.12
Classifier: Programming Language :: Python :: 3.13
Classifier: Topic :: Software Development :: Libraries :: Python Modules
Requires-Python: <4.0,>=3.9
